{
  "timestamp": "2025-10-17T00:00:00.000Z",
  "project": "BarodaTek Champions Arena",
  "version": "2.0.0",
  "environment": "pre-production",
  "auditor": "GitHub Copilot",
  "tests": {
    "unit": {
      "status": "passed",
      "passed": 8,
      "failed": 0,
      "total": 8,
      "duration": "0.874s",
      "details": [
        "GET /api/health - ✅ PASSED",
        "GET /api/contracts - ✅ PASSED",
        "POST /api/contracts - ✅ PASSED",
        "GET /api/analytics - ✅ PASSED",
        "GET /api/monitoring/status - ✅ PASSED",
        "POST /api/chat - ✅ PASSED",
        "POST /api/generate - ✅ PASSED",
        "GET /api/games/questions - ✅ PASSED"
      ]
    },
    "integration": {
      "status": "not-run",
      "reason": "Requires local server instance"
    },
    "api": {
      "status": "passed",
      "endpoints": [
        {
          "endpoint": "/api/health",
          "method": "GET",
          "implemented": true,
          "tested": true,
          "status": "✅ WORKING"
        },
        {
          "endpoint": "/api/contracts",
          "method": "GET",
          "implemented": true,
          "tested": true,
          "status": "✅ WORKING"
        },
        {
          "endpoint": "/api/contracts",
          "method": "POST",
          "implemented": true,
          "tested": true,
          "status": "✅ WORKING"
        },
        {
          "endpoint": "/api/analytics",
          "method": "GET",
          "implemented": true,
          "tested": true,
          "status": "✅ WORKING"
        },
        {
          "endpoint": "/api/monitoring/status",
          "method": "GET",
          "implemented": true,
          "tested": true,
          "status": "✅ WORKING"
        },
        {
          "endpoint": "/api/chat",
          "method": "POST",
          "implemented": true,
          "tested": true,
          "status": "✅ WORKING"
        },
        {
          "endpoint": "/api/generate",
          "method": "POST",
          "implemented": true,
          "tested": true,
          "status": "✅ WORKING"
        },
        {
          "endpoint": "/api/games/questions",
          "method": "GET",
          "implemented": true,
          "tested": true,
          "status": "✅ WORKING"
        },
        {
          "endpoint": "/api/demo",
          "method": "POST",
          "implemented": true,
          "tested": false,
          "status": "⚠️ SIMULATED (security limitation)"
        },
        {
          "endpoint": "/api/explorer/test",
          "method": "POST",
          "implemented": true,
          "tested": false,
          "status": "✅ IMPLEMENTED"
        }
      ]
    },
    "security": {
      "status": "partial",
      "issues": [
        {
          "severity": "high",
          "issue": "CSP disabled in api/index.js",
          "file": "api/index.js",
          "line": "contentSecurityPolicy: false",
          "recommendation": "Enable CSP with proper directives for production"
        },
        {
          "severity": "medium",
          "issue": "No rate limiting in serverless API",
          "recommendation": "Consider Vercel edge middleware or API gateway for rate limiting"
        },
        {
          "severity": "low",
          "issue": "Authentication not implemented",
          "recommendation": "Phase 2 feature - not blocking MVP deployment"
        }
      ],
      "passed": [
        "No hardcoded secrets detected",
        "Input validation present on POST endpoints",
        "CORS configured",
        "Helmet middleware enabled",
        "Error handling implemented"
      ]
    },
    "links": {
      "status": "not-run",
      "reason": "Script created but not executed - run 'npm run link-check' manually"
    },
    "frontend": {
      "status": "needs-manual-testing",
      "features": [
        {
          "feature": "Chat Input/Output",
          "status": "⚠️ NEEDS TESTING",
          "note": "API endpoint works, frontend integration needs verification"
        },
        {
          "feature": "Code Generator",
          "status": "⚠️ NEEDS TESTING",
          "note": "API endpoint works, frontend integration needs verification"
        },
        {
          "feature": "API Explorer",
          "status": "⚠️ NEEDS TESTING",
          "note": "API endpoint works, frontend integration needs verification"
        },
        {
          "feature": "Mini-games",
          "status": "⚠️ NEEDS TESTING",
          "note": "Question data available, game logic needs verification"
        },
        {
          "feature": "Profile Image",
          "status": "✅ FIXED",
          "note": "File replaced with proper image (170KB)"
        },
        {
          "feature": "Logo Display",
          "status": "✅ FIXED",
          "note": "Logo added to navbar, hero, footer, favicon"
        }
      ]
    }
  },
  "filesFixed": [
    "api/index.js - Added missing endpoints",
    "jbaroda-profile.jpg - Replaced corrupted file",
    "index.html - Updated logo and profile image paths",
    "package.json - Added test scripts and dependencies",
    "jest.config.js - Created",
    "tests/api.test.js - Created",
    "tests/setup.js - Created",
    "scripts/link-checker.js - Created",
    "scripts/security-audit.js - Created",
    "DEPLOY_NOTES.md - Created",
    "AUDIT_REPORT.md - Created"
  ],
  "warnings": [
    "WebSocket functionality incompatible with Vercel serverless - uses HTTP polling instead",
    "CSP disabled for compatibility - should be enabled before full production",
    "Authentication flows not implemented - Phase 2 feature",
    "Code execution is simulated only - requires sandbox for real execution",
    "Rate limiting not available in serverless - consider edge middleware",
    "Frontend UI interactions need manual browser testing",
    "Mini-game hint/scoring/localStorage logic needs verification",
    "External link validity not checked - run link-checker script"
  ],
  "blockers": [],
  "recommendations": [
    "Run 'npm run link-check' to verify external links",
    "Run 'npm run security-audit' for detailed security analysis",
    "Manually test chat, code generation, and games in browser",
    "Test on mobile devices for responsiveness",
    "Monitor Vercel logs after deployment for runtime errors",
    "Consider Phase 2 implementation for auth and WebSocket"
  ],
  "readyToDeploy": true,
  "deploymentReadiness": {
    "apiEndpoints": "✅ READY",
    "testCoverage": "✅ READY",
    "security": "⚠️ ACCEPTABLE (with known limitations)",
    "frontend": "⚠️ NEEDS MANUAL VERIFICATION",
    "documentation": "✅ READY",
    "overallStatus": "⚠️ READY FOR MANUAL VERIFICATION"
  },
  "nextSteps": [
    "1. Review DEPLOY_NOTES.md thoroughly",
    "2. Run 'npm start' and test locally",
    "3. Test chat, code generation, API explorer, and at least one game",
    "4. Run 'npm run link-check' (optional but recommended)",
    "5. Deploy with 'vercel --prod --yes'",
    "6. Verify on https://barodatek.com",
    "7. Monitor Vercel logs for any errors",
    "8. Mark deployment as complete"
  ],
  "estimatedDeploymentTime": "5-10 minutes",
  "rollbackPlan": "Use 'vercel rollback' if issues detected post-deployment"
}
